himosoft_payment_logging_client/__init__.py
himosoft_payment_logging_client/cli.py
himosoft_payment_logging_client/client.py
himosoft_payment_logging_client/config.py
himosoft_payment_logging_client/exceptions.py
himosoft_payment_logging_client-1.0.0.dist-info/licenses/LICENSE
himosoft_payment_logging_client-1.0.0.dist-info/METADATA
himosoft_payment_logging_client-1.0.0.dist-info/WHEEL
himosoft_payment_logging_client-1.0.0.dist-info/entry_points.txt
himosoft_payment_logging_client-1.0.0.dist-info/top_level.txt
himosoft_payment_logging_client-1.0.0.dist-info/RECORD
