Metadata-Version: 2.4
Name: himosoft-payment-logging-client
Version: 1.0.0
Summary: A Python client library for integrating with the Himosoft Payment Logging API
Author-email: Himosoft <support@himosoft.com>
Maintainer-email: Himosoft <support@himosoft.com>
License: MIT
Project-URL: Homepage, https://github.com/Swe-HimelRana/himosoft-payment-logging-client
Project-URL: Documentation, https://github.com/Swe-HimelRana/himosoft-payment-logging-client#readme
Project-URL: Repository, https://github.com/Swe-HimelRana/himosoft-payment-logging-client
Project-URL: Bug Tracker, https://github.com/Swe-HimelRana/himosoft-payment-logging-client/issues
Project-URL: Source Code, https://github.com/Swe-HimelRana/himosoft-payment-logging-client
Keywords: payment,logging,api,client,himosoft
Classifier: Development Status :: 4 - Beta
Classifier: Intended Audience :: Developers
Classifier: License :: OSI Approved :: MIT License
Classifier: Operating System :: OS Independent
Classifier: Programming Language :: Python :: 3
Classifier: Programming Language :: Python :: 3.8
Classifier: Programming Language :: Python :: 3.9
Classifier: Programming Language :: Python :: 3.10
Classifier: Programming Language :: Python :: 3.11
Classifier: Programming Language :: Python :: 3.12
Classifier: Topic :: Software Development :: Libraries :: Python Modules
Classifier: Topic :: Office/Business :: Financial
Requires-Python: >=3.8
License-File: LICENSE
Requires-Dist: requests>=2.25.0
Requires-Dist: python-decouple>=3.6
Provides-Extra: dev
Requires-Dist: pytest>=6.0; extra == "dev"
Requires-Dist: pytest-cov>=2.10; extra == "dev"
Requires-Dist: black>=21.0; extra == "dev"
Requires-Dist: flake8>=3.8; extra == "dev"
Requires-Dist: responses>=0.13.0; extra == "dev"
Requires-Dist: build>=1.0.0; extra == "dev"
Requires-Dist: twine>=4.0.0; extra == "dev"
Dynamic: license-file
